simulation/sram8t.v

module sram8t #(
    parameter ADDR_WIDTH = 4,     // 16 locations
    parameter DATA_WIDTH = 8      // 8-bit word
)(
    input wire clk,
    input wire rst_n,             // Active-low reset
    input wire cs,                // Chip Select (low power gating)
    input wire re,                // Read Enable
    input wire we,                // Write Enable
    input wire [ADDR_WIDTH-1:0] addr,
    input wire [DATA_WIDTH-1:0] din,
    output reg [DATA_WIDTH-1:0] dout
);

    // Internal SRAM array
    reg [DATA_WIDTH-1:0] mem [0:(1<<ADDR_WIDTH)-1];

    // Internal power-aware enable signal
    wire access_en = cs & (re | we); // Enable only if chip is selected and any access

    always @(posedge clk or negedge rst_n) begin
        if (!rst_n)
            dout <= 0;
        else if (access_en) begin
            if (we)
                mem[addr] <= din;        // Write operation
            else if (re)
                dout <= mem[addr];       // Read operation
        end else begin
            // Optional: simulate low power state (no switching)
            dout <= {DATA_WIDTH{1'bz}};  // High-Z to simulate inactivity
        end
    end
endmodule

simulation/test.v


module test;

    localparam ADDR_WIDTH = 4;
    localparam DATA_WIDTH = 8;

    reg clk = 0;
    reg rst_n = 0;
    reg cs = 0;
    reg re = 0;
    reg we = 0;
    reg [ADDR_WIDTH-1:0] addr = 0;
    reg [DATA_WIDTH-1:0] din = 0;
    wire [DATA_WIDTH-1:0] dout;

    sram8t #(.ADDR_WIDTH(ADDR_WIDTH), .DATA_WIDTH(DATA_WIDTH)) uut (
        .clk(clk), .rst_n(rst_n), .cs(cs), .re(re), .we(we),
        .addr(addr), .din(din), .dout(dout)
    );

    always #5 clk = ~clk;

    initial begin
        $dumpfile("wave.vcd");
        $dumpvars(0, test);

        #10 rst_n = 1;

        // Write
        #10 cs = 1; we = 1; addr = 4'h2; din = 8'hAA;
        #10 we = 0;

        // Read
        #10 re = 1;
        #10 re = 0;

        // Done
        #20 $finish;
    end

endmodule

simulation/wave.vcd
$date
	Wed Jul  9 11:32:39 2025
$end
$version
	Icarus Verilog
$end
$timescale
	1s
$end
$scope module test $end
$var wire 8 ! dout [7:0] $end
$var reg 4 " addr [3:0] $end
$var reg 1 # clk $end
$var reg 1 $ cs $end
$var reg 8 % din [7:0] $end
$var reg 1 & re $end
$var reg 1 ' rst_n $end
$var reg 1 ( we $end
$scope module uut $end
$var wire 1 ) access_en $end
$var wire 4 * addr [3:0] $end
$var wire 1 # clk $end
$var wire 1 $ cs $end
$var wire 8 + din [7:0] $end
$var wire 1 & re $end
$var wire 1 ' rst_n $end
$var wire 1 ( we $end
$var reg 8 , dout [7:0] $end
$upscope $end
$upscope $end
$enddefinitions $end
#0
$dumpvars
b0 ,
b0 +
b0 *
0)
0(
0'
0&
b0 %
0$
0#
b0 "
b0 !
$end
#5
1#
#10
0#
1'
#15
bz !
bz ,
1#
#20
1)
0#
b10101010 %
b10101010 +
b10 "
b10 *
1(
1$
#25
1#
#30
0)
0#
0(
#35
1#
#40
1)
0#
1&
#45
b10101010 !
b10101010 ,
1#
#50
0)
0#
0&
#55
bz !
bz ,
1#
